mtf/__init__.py
mtf/__main__.py
mtf/line.py
pymtf-0.1.0.dist-info/METADATA
pymtf-0.1.0.dist-info/WHEEL
pymtf-0.1.0.dist-info/RECORD
