Metadata-Version: 2.3
Name: pymtf
Version: 0.1.0
Summary: 
Author: Mike Sutton
Requires-Python: >=3.13
Classifier: Programming Language :: Python :: 3
Classifier: Programming Language :: Python :: 3.13
Requires-Dist: ipython (>=9.4.0,<10.0.0)
Requires-Dist: matplotlib (>=3.10.5,<4.0.0)
Requires-Dist: numpy (>=2.3.2,<3.0.0)
Requires-Dist: pillow (>=11.3.0,<12.0.0)
Requires-Dist: scipy (>=1.16.1,<2.0.0)
